doccloud_cli/__init__.py
doccloud_cli/__main__.py
doccloud_cli/main.py
doccloud_cli-1.0.7.dist-info/entry_points.txt
doccloud_cli-1.0.7.dist-info/LICENSE
doccloud_cli-1.0.7.dist-info/METADATA
doccloud_cli-1.0.7.dist-info/WHEEL
doccloud_cli-1.0.7.dist-info/RECORD
