Metadata-Version: 2.3
Name: doccloud-cli
Version: 1.0.7
Summary: A CLI for the DocumentCloud platform.
Author: Noah Dangerfield
Author-email: noah.dangerfield@gmail.com
Requires-Python: >=3.8
Classifier: Programming Language :: Python :: 3
Classifier: Operating System :: OS Independent
Classifier: License :: OSI Approved :: MIT License
Requires-Dist: python-documentcloud (>=4.4.0,<5.0.0)
Requires-Dist: typer (>=0.15.1,<0.16.0)
Project-URL: Homepage, https://github.com/leadbraw/doccloud-cli
Project-URL: Issues, https://github.com/leadbraw/doccloud-cli/issues
